wagtail_transcription/__init__.py
wagtail_transcription/apps.py
wagtail_transcription/decorators.py
wagtail_transcription/edit_handlers.py
wagtail_transcription/tokens.py
wagtail_transcription/urls.py
wagtail_transcription/wagtail_hooks.py
wagtail_transcription/widgets.py
wagtail_transcription/migrations/0001_initial.py
wagtail_transcription/migrations/0002_alter_transcription_options.py
wagtail_transcription/migrations/__init__.py
wagtail_transcription/models/__init__.py
wagtail_transcription/models/transcription.py
wagtail_transcription/static/wagtail_transcription/js/widgets/change_transcription_field.js
wagtail_transcription/static/wagtail_transcription/js/widgets/fetch_message.js
wagtail_transcription/static/wagtail_transcription/js/widgets/notify.js
wagtail_transcription/static/wagtail_transcription/js/widgets/transcription.js
wagtail_transcription/static/wagtail_transcription/style/widgets/fetch_message.css
wagtail_transcription/static/wagtail_transcription/style/widgets/notify.css
wagtail_transcription/static/wagtail_transcription/style/widgets/transcription.css
wagtail_transcription/templates/wagtail_transcription/admin/video_data.html
wagtail_transcription/templates/wagtail_transcription/components/transcription_info_popup.html
wagtail_transcription/templates/wagtail_transcription/components/transcription_received_popup.html
wagtail_transcription/templates/wagtail_transcription/components/validation_error_popups/base.html
wagtail_transcription/templates/wagtail_transcription/components/validation_error_popups/invalid_video_id.html
wagtail_transcription/templates/wagtail_transcription/components/validation_error_popups/no_parent_instance.html
wagtail_transcription/templates/wagtail_transcription/components/validation_error_popups/same_video_transcription.html
wagtail_transcription/templates/wagtail_transcription/widgets/transcription.html
wagtail_transcription/templates/wagtailadmin/base.html
wagtail_transcription/templatetags/__init__.py
wagtail_transcription-0.0.16.dist-info/LICENSE
wagtail_transcription-0.0.16.dist-info/METADATA
wagtail_transcription-0.0.16.dist-info/WHEEL
wagtail_transcription-0.0.16.dist-info/top_level.txt
wagtail_transcription-0.0.16.dist-info/RECORD
