Metadata-Version: 2.1
Name: wagtail-transcription
Version: 0.0.16
Home-page: https://github.com/LilJack118/wagtail-transcription
Author: LilJack118
Author-email: jakub@kachange.com
Project-URL: Bug Tracker, https://github.com/LilJack118/wagtail-transcription/issues
Keywords: wagtail django
Classifier: Programming Language :: Python :: 3
Classifier: License :: OSI Approved :: MIT License
Classifier: Operating System :: OS Independent
Requires-Python: >=3.9
License-File: LICENSE
Requires-Dist: Wagtail >=3.0
Requires-Dist: django-notifications-hq
Requires-Dist: python-docx
Requires-Dist: pytube
